{
	"format_version": "1.21.40",
	"minecraft:block": {
		"description": {
			"identifier": "vc:advanced_observer",
			"menu_category": {
				"category": "items",
				"group": "itemGroup.name.redstone"
			},
			"traits": {
				"minecraft:placement_direction": {
					"enabled_states": [
						"minecraft:facing_direction"
					]
				}
			},
			"states": {
				"vc:lit_bit": [
					false,
					true
				],
				"vc:changeable": [
					true,
					false
				]
			}
		},
		"components": {
			"minecraft:geometry": "minecraft:geometry.full_block",
			"minecraft:light_dampening": 5,
			"minecraft:map_color": "#27272b",
			"minecraft:destructible_by_mining": {
				"seconds_to_destroy": 20
			},
			"minecraft:custom_components": [
				"vc:advanced_observer"
			],
			"minecraft:redstone_conductivity": {
				"allows_wire_to_step_down": true,
				"redstone_conductor": true
			},
			"minecraft:display_name": "tile.vc:advanced_observer.name",
			"minecraft:tick": {
				"interval_range": [
					1,
					1
				],
				"looping": true
			},
			"minecraft:material_instances": {
				"*": {
					"texture": "advanced_observer_side",
					"render_method": "alpha_test"
				},
				"south": {
					"texture": "advanced_observer_front",
					"render_method": "alpha_test"
				},
				"north": {
					"texture": "advanced_observer_back",
					"render_method": "alpha_test"
				},
				"up": {
					"texture": "advanced_observer_top",
					"render_method": "alpha_test"
				},
				"down": {
					"texture": "observer_bottom",
					"render_method": "alpha_test"
				}
			}
		},
		"permutations": [
			{
				"condition": "query.block_state('vc:lit_bit') == true",
				"components": {
					"minecraft:material_instances": {
						"*": {
							"texture": "advanced_observer_side",
							"render_method": "alpha_test"
						},
						"south": {
							"texture": "advanced_observer_front_lit",
							"render_method": "alpha_test"
						},
						"north": {
							"texture": "advanced_observer_back_lit",
							"render_method": "alpha_test"
						},
						"up": {
							"texture": "advanced_observer_top",
							"render_method": "alpha_test"
						},
						"down": {
							"texture": "observer_bottom",
							"render_method": "alpha_test"
						}
					}
				}
			},
			{
				"condition": "query.block_state('minecraft:facing_direction') == 'north'",
				"components": {
					"minecraft:transformation": {
						"rotation": [
							0,
							180,
							0
						]
					}
				}
			},
			{
				"condition": "query.block_state('minecraft:facing_direction') == 'east'",
				"components": {
					"minecraft:transformation": {
						"rotation": [
							0,
							90,
							0
						]
					}
				}
			},
			{
				"condition": "query.block_state('minecraft:facing_direction') == 'west'",
				"components": {
					"minecraft:transformation": {
						"rotation": [
							0,
							270,
							0
						]
					}
				}
			},
			{
				"condition": "query.block_state('minecraft:facing_direction') == 'up'",
				"components": {
					"minecraft:transformation": {
						"rotation": [
							-90,
							0,
							0
						]
					}
				}
			},
			{
				"condition": "query.block_state('minecraft:facing_direction') == 'down'",
				"components": {
					"minecraft:transformation": {
						"rotation": [
							90,
							0,
							0
						]
					}
				}
			}
		]
	}
}