{
	"format_version": "1.12.0",
	"minecraft:geometry": [
		{
			"description": {
				"identifier": "geometry.humanoid.thicc",
				"texture_width": 64,
				"texture_height": 64,
				"visible_bounds_width": 4,
				"visible_bounds_height": 6,
				"visible_bounds_offset": [0, 2, 0]
			},
			"bones": [
				{
					"name": "root",
					"pivot": [0, 0, 0]
				},
				{
					"name": "waist",
					"parent": "root",
					"pivot": [0, 12, 0]
				},
				{
					"name": "body",
					"parent": "waist",
					"pivot": [0, 24, 0],
					"cubes": [
						{
							"origin": [-3.7, 32.75, -1.25],
							"size": [9.5, 10.5, 2],
							"uv": {
								"north": {"uv": [21, 22], "uv_size": [6, 3]},
								"up": {"uv": [27, 23], "uv_size": [-6, -1]},
								"down": {"uv": [21, 22], "uv_size": [6, 1]}
							}
						},
						{
							"origin": [-7.5, 30.25, -1],
							"size": [6.5, 6, 7.5],
							"uv": {
								"north": {"uv": [21, 30], "uv_size": [2, 2]},
								"east": {"uv": [21, 30], "uv_size": [2, 2]},
								"south": {"uv": [21, 30], "uv_size": [2, 2]},
								"west": {"uv": [21, 30], "uv_size": [2, 2]},
								"up": {"uv": [23, 32], "uv_size": [-2, -2]},
								"down": {"uv": [21, 30], "uv_size": [2, 2]}
							}
						},
						{
							"origin": [-2.25, 30.5, -1],
							"size": [7, 6, 8],
							"uv": {
								"north": {"uv": [21, 30], "uv_size": [2, 2]},
								"east": {"uv": [21, 30], "uv_size": [2, 2]},
								"south": {"uv": [21, 30], "uv_size": [2, 2]},
								"west": {"uv": [21, 30], "uv_size": [2, 2]},
								"up": {"uv": [23, 32], "uv_size": [-2, -2]},
								"down": {"uv": [21, 30], "uv_size": [2, 2]}
							}
						},
						{
							"origin": [-2, 25, -0.75],
							"size": [6, 6, 7.5],
							"uv": {
								"north": {"uv": [23, 30], "uv_size": [2, 2]},
								"east": {"uv": [23, 30], "uv_size": [2, 2]},
								"south": {"uv": [21, 30], "uv_size": [2, 2]},
								"west": {"uv": [23, 30], "uv_size": [2, 2]},
								"up": {"uv": [25, 32], "uv_size": [-2, -2]},
								"down": {"uv": [23, 30], "uv_size": [2, 2]}
							}
						},
						{
							"origin": [-1.25, 25, -4.5],
							"size": [5.5, 6, 7.5],
							"pivot": [-7.5, 30, 9.25],
							"rotation": [0, -22.5, 0],
							"uv": {
								"north": {"uv": [24, 30], "uv_size": [2, 2]},
								"east": {"uv": [24, 30], "uv_size": [2, 2]},
								"south": {"uv": [33, 30], "uv_size": [2, 2]},
								"west": {"uv": [24, 30], "uv_size": [2, 2]},
								"up": {"uv": [26, 32], "uv_size": [-2, -2]},
								"down": {"uv": [24, 30], "uv_size": [2, 2]}
							}
						},
						{
							"origin": [-4.25, 25, 2.25],
							"size": [5.5, 6, 7.5],
							"pivot": [-7.5, 30, 9.25],
							"rotation": [0, 22.5, 0],
							"uv": {
								"north": {"uv": [21, 30], "uv_size": [2, 2]},
								"east": {"uv": [21, 30], "uv_size": [2, 2]},
								"south": {"uv": [38, 30], "uv_size": [2, 2]},
								"west": {"uv": [21, 30], "uv_size": [2, 2]},
								"up": {"uv": [23, 32], "uv_size": [-2, -2]},
								"down": {"uv": [21, 30], "uv_size": [2, 2]}
							}
						},
						{
							"origin": [3, 30.25, -1],
							"size": [6.5, 6, 7.5],
							"uv": {
								"north": {"uv": [21, 30], "uv_size": [2, 2]},
								"east": {"uv": [21, 30], "uv_size": [2, 2]},
								"south": {"uv": [21, 30], "uv_size": [2, 2]},
								"west": {"uv": [21, 30], "uv_size": [2, 2]},
								"up": {"uv": [23, 32], "uv_size": [-2, -2]},
								"down": {"uv": [21, 30], "uv_size": [2, 2]}
							}
						},
						{
							"origin": [1.7911, 58.25, -2],
							"size": [9.5, 3.5, 7],
							"pivot": [10.54105, 29.58859, 9.25],
							"rotation": [0, 0, -22.5],
							"uv": {
								"north": {"uv": [26, 20], "uv_size": [2, 2]},
								"east": {"uv": [28, 20], "uv_size": [2, 2]},
								"south": {"uv": [32, 20], "uv_size": [2, 2]},
								"up": {"uv": [48, 20], "uv_size": [-4, -4]}
							}
						},
						{
							"origin": [-8.79105, 59.25, -2],
							"size": [9.5, 3.5, 7],
							"pivot": [-10.29105, 29.58859, 9.25],
							"rotation": [0, 0, 22.5],
							"uv": {
								"north": {"uv": [26, 20], "uv_size": [2, 2]},
								"south": {"uv": [32, 20], "uv_size": [2, 2]},
								"west": {"uv": [28, 20], "uv_size": [2, 2]},
								"up": {"uv": [40, 52], "uv_size": [-4, -4]}
							}
						},
						{
							"origin": [-10.1, 42.75, -2.25],
							"size": [22.5, 12.5, 11.6],
							"uv": {
								"north": {"uv": [20, 22], "uv_size": [8, 5]},
								"east": {"uv": [16, 22], "uv_size": [4, 5]},
								"south": {"uv": [32, 22], "uv_size": [8, 5]},
								"west": {"uv": [28, 22], "uv_size": [4, 5]},
								"up": {"uv": [40, 23], "uv_size": [-8, -3]},
								"down": {"uv": [32, 20], "uv_size": [8, 3]}
							}
						},
						{
							"origin": [-2.7116, 29.97347, -0.75],
							"size": [9.5, 12, 8],
							"pivot": [-8.21539, 29.97347, 9.25],
							"rotation": [0, 0, -22.5],
							"uv": {
								"north": {"uv": [32, 20], "uv_size": [7, 8]},
								"east": {"uv": [32, 20], "uv_size": [8, 8]},
								"south": {"uv": [32, 20], "uv_size": [7, 8]},
								"down": {"uv": [28, 16], "uv_size": [19, 20]}
							}
						},
						{
							"origin": [-5.7116, 39.82686, -0.75],
							"size": [9.5, 12, 8],
							"pivot": [-6.4616, 31.82686, 9.25],
							"rotation": [0, 0, 22.5],
							"uv": {
								"north": {"uv": [28, 20], "uv_size": [7, 8]},
								"south": {"uv": [28, 20], "uv_size": [7, 8]},
								"west": {"uv": [28, 20], "uv_size": [8, 8]},
								"down": {"uv": [28, 16], "uv_size": [19, 20]}
							}
						},
						{
							"origin": [-4.5, 33, -1.75],
							"size": [11, 16, 10],
							"uv": {
								"north": {"uv": [28, 24], "uv_size": [8, 6]},
								"east": {"uv": [16, 25], "uv_size": [4, 6]},
								"south": {"uv": [32, 20], "uv_size": [8, 10]},
								"west": {"uv": [28, 25], "uv_size": [4, 6]},
								"down": {"uv": [28, 16], "uv_size": [8, 4]}
							}
						},
						{
							"origin": [1.5, 33.25, -2.5],
							"size": [4, 3, 1.5],
							"uv": {
								"north": {"uv": [25, 28], "uv_size": [3, 2]},
								"east": {"uv": [25, 28], "uv_size": [3, 2]},
								"south": {"uv": [25, 28], "uv_size": [3, 2]},
								"west": {"uv": [25, 28], "uv_size": [3, 2]},
								"up": {"uv": [28, 30], "uv_size": [-3, -2]},
								"down": {"uv": [25, 28], "uv_size": [3, 2]}
							}
						},
						{
							"origin": [-3.05, 33.25, -2.5],
							"size": [4, 3, 1.5],
							"uv": {
								"north": {"uv": [20, 28], "uv_size": [3, 2]},
								"east": {"uv": [20, 28], "uv_size": [3, 2]},
								"south": {"uv": [20, 28], "uv_size": [3, 2]},
								"west": {"uv": [20, 28], "uv_size": [3, 2]},
								"up": {"uv": [23, 30], "uv_size": [-3, -2]},
								"down": {"uv": [20, 28], "uv_size": [3, 2]}
							}
						},
						{
							"origin": [1.51, 36.5, -2.6],
							"size": [4.5, 3, 1.7],
							"uv": {
								"north": {"uv": [25, 27], "uv_size": [3, 2]},
								"east": {"uv": [25, 27], "uv_size": [3, 2]},
								"south": {"uv": [25, 27], "uv_size": [3, 2]},
								"west": {"uv": [25, 27], "uv_size": [3, 2]},
								"up": {"uv": [28, 29], "uv_size": [-3, -2]},
								"down": {"uv": [25, 27], "uv_size": [3, 2]}
							}
						},
						{
							"origin": [-3.6, 36.5, -2.6],
							"size": [4.5, 3, 1.7],
							"uv": {
								"north": {"uv": [20, 27], "uv_size": [3, 2]},
								"east": {"uv": [20, 27], "uv_size": [3, 2]},
								"south": {"uv": [20, 27], "uv_size": [3, 2]},
								"west": {"uv": [20, 27], "uv_size": [3, 2]},
								"up": {"uv": [23, 29], "uv_size": [-3, -2]},
								"down": {"uv": [20, 27], "uv_size": [3, 2]}
							}
						},
						{
							"origin": [1.5, 40, -2.75],
							"size": [5, 3, 2],
							"uv": {
								"north": {"uv": [25, 26], "uv_size": [3, 2]},
								"east": {"uv": [25, 26], "uv_size": [3, 2]},
								"south": {"uv": [25, 26], "uv_size": [3, 2]},
								"west": {"uv": [25, 26], "uv_size": [3, 2]},
								"up": {"uv": [28, 28], "uv_size": [-3, -2]},
								"down": {"uv": [25, 26], "uv_size": [3, 2]}
							}
						},
						{
							"origin": [-4.25, 40, -2.75],
							"size": [5, 3, 2],
							"uv": {
								"north": {"uv": [20, 26], "uv_size": [3, 2]},
								"east": {"uv": [20, 26], "uv_size": [3, 2]},
								"south": {"uv": [20, 26], "uv_size": [3, 2]},
								"west": {"uv": [20, 26], "uv_size": [3, 2]},
								"up": {"uv": [23, 28], "uv_size": [-3, -2]},
								"down": {"uv": [20, 26], "uv_size": [3, 2]}
							}
						},
						{
							"origin": [-6.5, 43.3, -3],
							"size": [6, 3.9, 2.5],
							"uv": {
								"north": {"uv": [20, 24], "uv_size": [3, 1.8]},
								"east": {"uv": [20, 24], "uv_size": [3, 1.8]},
								"south": {"uv": [20, 24], "uv_size": [3, 1.8]},
								"west": {"uv": [20, 24], "uv_size": [3, 1.8]},
								"up": {"uv": [23, 25.8], "uv_size": [-3, -1.8]},
								"down": {"uv": [20, 24], "uv_size": [3, 1.8]}
							}
						},
						{
							"origin": [2.5, 43.3, -3],
							"size": [6, 3.9, 2.5],
							"uv": {
								"north": {"uv": [25, 24], "uv_size": [3, 1.8]},
								"east": {"uv": [25, 24], "uv_size": [3, 1.8]},
								"south": {"uv": [25, 24], "uv_size": [3, 1.8]},
								"west": {"uv": [25, 24], "uv_size": [3, 1.8]},
								"up": {"uv": [28, 25.8], "uv_size": [-3, -1.8]},
								"down": {"uv": [25, 24], "uv_size": [3, 1.8]}
							}
						},
						{
							"origin": [-3.8, 54, -2.25],
							"size": [9.5, 4, 8],
							"uv": {
								"north": {"uv": [22, 20], "uv_size": [4, 2]},
								"east": {"uv": [20, 19], "uv_size": [2, 2]},
								"south": {"uv": [34, 20], "uv_size": [4, 2]},
								"west": {"uv": [26, 19], "uv_size": [2, 2]}
							}
						},
						{
							"origin": [-3.5, 44.75, -8.5],
							"size": [11.5, 11.5, 5],
							"pivot": [-7.5, 29, 9.25],
							"rotation": [0, -22.5, 0],
							"uv": {
								"north": {"uv": [24, 22], "uv_size": [4, 3]},
								"east": {"uv": [24, 22], "uv_size": [2, 3]},
								"south": {"uv": [24, 22], "uv_size": [4, 3]},
								"west": {"uv": [26, 22], "uv_size": [2, 3]},
								"up": {"uv": [28, 23], "uv_size": [-4, -1]},
								"down": {"uv": [24, 24], "uv_size": [4, 1]}
							}
						},
						{
							"origin": [-5.75, 44.75, -8.5],
							"size": [11.5, 11.5, 5],
							"pivot": [7.5, 29, 9.25],
							"rotation": [0, 22.5, 0],
							"uv": {
								"north": {"uv": [20, 22], "uv_size": [4, 3]},
								"east": {"uv": [20, 22], "uv_size": [2, 3]},
								"south": {"uv": [20, 22], "uv_size": [4, 3]},
								"west": {"uv": [22, 22], "uv_size": [2, 3]},
								"up": {"uv": [24, 23], "uv_size": [-4, -1]},
								"down": {"uv": [20, 24], "uv_size": [4, 1]}
							}
						}
					]
				},
				{
					"name": "head",
					"parent": "body",
					"pivot": [0, 57.9, 0],
					"cubes": [
						{
							"origin": [-3, 57.9, -4],
							"size": [8, 8, 8],
							"uv": {
								"north": {"uv": [8, 8], "uv_size": [8, 8]},
								"east": {"uv": [0, 8], "uv_size": [8, 8]},
								"south": {"uv": [24, 8], "uv_size": [8, 8]},
								"west": {"uv": [16, 8], "uv_size": [8, 8]},
								"up": {"uv": [16, 8], "uv_size": [-8, -8]},
								"down": {"uv": [16, 0], "uv_size": [8, 8]}
							}
						},
						{
							"origin": [-3, 57.9, -4],
							"size": [8, 8, 8],
							"inflate": 0.5,
							"uv": {
								"north": {"uv": [40, 8], "uv_size": [8, 8]},
								"east": {"uv": [32, 8], "uv_size": [8, 8]},
								"south": {"uv": [56, 8], "uv_size": [8, 8]},
								"west": {"uv": [48, 8], "uv_size": [8, 8]},
								"up": {"uv": [48, 8], "uv_size": [-8, -8]},
								"down": {"uv": [48, 0], "uv_size": [8, 8]}
							}
						}
					]
				},
				{
					"name": "cape",
					"parent": "body",
					"pivot": [1, 52, 5]
				},
				{
					"name": "rightArm",
					"parent": "body",
					"pivot": [-10.66971, 55.18048, 2.51875],
					"cubes": [
						{
							"origin": [-17.40884, 28.44194, -1.4],
							"size": [9.1, 15.6, 8.6],
							"pivot": [14.29116, 41.84194, 9.25],
							"rotation": [0, 0, 22.5],
							"uv": {
								"north": {"uv": [36, 52], "uv_size": [4, 7]},
								"east": {"uv": [32, 52], "uv_size": [4, 7]},
								"south": {"uv": [44, 52], "uv_size": [4, 7]},
								"west": {"uv": [40, 52], "uv_size": [4, 7]},
								"up": {"uv": [40, 52], "uv_size": [-4, -4]},
								"down": {"uv": [36, 56], "uv_size": [4, 4]}
							}
						},
						{
							"origin": [-19.7, 28.3419, -0.7],
							"size": [7.7, 14.2, 7.2],
							"uv": {
								"north": {"uv": [36, 57], "uv_size": [4, 6]},
								"east": {"uv": [32, 57], "uv_size": [4, 6]},
								"south": {"uv": [44, 57], "uv_size": [4, 6]},
								"west": {"uv": [40, 57], "uv_size": [4, 6]},
								"up": {"uv": [40, 61], "uv_size": [-4, -4]},
								"down": {"uv": [36, 59], "uv_size": [4, 4]}
							}
						},
						{
							"origin": [-17.7, 20.34194, 0.45],
							"size": [3.7, 8.2, 5.2],
							"uv": {
								"north": {"uv": [36, 64], "uv_size": [4, -4]},
								"east": {"uv": [32, 64], "uv_size": [4, -4]},
								"south": {"uv": [44, 64], "uv_size": [4, -4]},
								"west": {"uv": [40, 64], "uv_size": [4, -4]},
								"down": {"uv": [36, 64], "uv_size": [4, -4]}
							}
						},
						{
							"origin": [-20.20884, 34.64194, -1.35],
							"size": [2.3, 6.6, 1.7],
							"pivot": [14.29116, 41.84194, 9.25],
							"rotation": [0, 0, -22.5],
							"uv": {
								"north": {"uv": [36, 64], "uv_size": [1, -2]},
								"east": {"uv": [36, 64], "uv_size": [1, -2]},
								"south": {"uv": [36, 64], "uv_size": [1, -2]},
								"west": {"uv": [36, 64], "uv_size": [1, -2]},
								"up": {"uv": [37, 62], "uv_size": [-1, 2]},
								"down": {"uv": [36, 64], "uv_size": [1, -2]}
							}
						},
						{
							"origin": [-23.97573, 29.64442, 0],
							"size": [2.1, 5.4, 1.3],
							"pivot": [13.22427, 42.14442, 10.05],
							"rotation": [0, 0, -22.5],
							"uv": {
								"north": {"uv": [36, 64], "uv_size": [1, -2]},
								"east": {"uv": [36, 64], "uv_size": [1, -2]},
								"south": {"uv": [36, 64], "uv_size": [1, -2]},
								"west": {"uv": [36, 64], "uv_size": [1, -2]},
								"up": {"uv": [37, 62], "uv_size": [-1, 2]},
								"down": {"uv": [36, 64], "uv_size": [1, -2]}
							}
						},
						{
							"origin": [-23.97573, 29.64442, 1.5],
							"size": [2.1, 5.4, 1.3],
							"pivot": [13.22427, 42.14442, 10.05],
							"rotation": [0, 0, -22.5],
							"uv": {
								"north": {"uv": [36, 64], "uv_size": [1, -2]},
								"east": {"uv": [36, 64], "uv_size": [1, -2]},
								"south": {"uv": [36, 64], "uv_size": [1, -2]},
								"west": {"uv": [36, 64], "uv_size": [1, -2]},
								"up": {"uv": [37, 62], "uv_size": [-1, 2]},
								"down": {"uv": [36, 64], "uv_size": [1, -2]}
							}
						},
						{
							"origin": [-23.97573, 29.64442, 3.1],
							"size": [2.1, 5.4, 1.3],
							"pivot": [13.22427, 42.14442, 10.05],
							"rotation": [0, 0, -22.5],
							"uv": {
								"north": {"uv": [36, 64], "uv_size": [1, -2]},
								"east": {"uv": [36, 64], "uv_size": [1, -2]},
								"south": {"uv": [36, 64], "uv_size": [1, -2]},
								"west": {"uv": [36, 64], "uv_size": [1, -2]},
								"up": {"uv": [37, 62], "uv_size": [-1, 2]},
								"down": {"uv": [36, 64], "uv_size": [1, -2]}
							}
						},
						{
							"origin": [-23.97573, 29.64442, 4.6],
							"size": [2.1, 5.4, 1.3],
							"pivot": [13.22427, 42.14442, 10.05],
							"rotation": [0, 0, -22.5],
							"uv": {
								"north": {"uv": [36, 64], "uv_size": [1, -2]},
								"east": {"uv": [36, 64], "uv_size": [1, -2]},
								"south": {"uv": [36, 64], "uv_size": [1, -2]},
								"west": {"uv": [36, 64], "uv_size": [1, -2]},
								"up": {"uv": [37, 62], "uv_size": [-1, 2]},
								"down": {"uv": [36, 64], "uv_size": [1, -2]}
							}
						}
					]
				},
				{
					"name": "rightItem",
					"parent": "rightArm",
					"pivot": [-13.66971, 24.18048, 2.51875]
				},
				{
					"name": "leftArm",
					"parent": "body",
					"pivot": [12.31546, 55.1805, 2.5188],
					"cubes": [
						{
							"origin": [14.55884, 28.34194, -0.7],
							"size": [7.7, 14.2, 7.2],
							"uv": {
								"north": {"uv": [44, 25], "uv_size": [4, 6]},
								"east": {"uv": [40, 25], "uv_size": [4, 6]},
								"south": {"uv": [52, 25], "uv_size": [4, 6]},
								"west": {"uv": [48, 25], "uv_size": [4, 6]},
								"up": {"uv": [48, 29], "uv_size": [-4, -4]},
								"down": {"uv": [44, 27], "uv_size": [4, 4]}
							}
						},
						{
							"origin": [16.80884, 20.34194, 0.45],
							"size": [3.7, 8.2, 5.2],
							"uv": {
								"north": {"uv": [44, 32], "uv_size": [4, -4]},
								"east": {"uv": [40, 32], "uv_size": [4, -4]},
								"south": {"uv": [52, 32], "uv_size": [4, -4]},
								"west": {"uv": [48, 32], "uv_size": [4, -4]},
								"down": {"uv": [44, 32], "uv_size": [4, -4]}
							}
						},
						{
							"origin": [20.75884, 34.64194, -1.35],
							"size": [2.3, 6.6, 1.7],
							"pivot": [-14.29116, 41.84194, 9.25],
							"rotation": [0, 0, 22.5],
							"uv": {
								"north": {"uv": [47, 32], "uv_size": [1, -2]},
								"east": {"uv": [47, 32], "uv_size": [1, -2]},
								"south": {"uv": [47, 32], "uv_size": [1, -2]},
								"west": {"uv": [47, 32], "uv_size": [1, -2]},
								"up": {"uv": [48, 30], "uv_size": [-1, 2]},
								"down": {"uv": [47, 32], "uv_size": [1, -2]}
							}
						},
						{
							"origin": [24.82573, 29.64442, 0],
							"size": [2.1, 5.4, 1.3],
							"pivot": [-13.22427, 42.14442, 10.05],
							"rotation": [0, 0, 22.5],
							"uv": {
								"north": {"uv": [47, 32], "uv_size": [1, -2]},
								"east": {"uv": [47, 32], "uv_size": [1, -2]},
								"south": {"uv": [47, 32], "uv_size": [1, -2]},
								"west": {"uv": [47, 32], "uv_size": [1, -2]},
								"up": {"uv": [48, 30], "uv_size": [-1, 2]},
								"down": {"uv": [47, 32], "uv_size": [1, -2]}
							}
						},
						{
							"origin": [24.82573, 29.64442, 1.5],
							"size": [2.1, 5.4, 1.3],
							"pivot": [-13.22427, 42.14442, 10.05],
							"rotation": [0, 0, 22.5],
							"uv": {
								"north": {"uv": [47, 32], "uv_size": [1, -2]},
								"east": {"uv": [47, 32], "uv_size": [1, -2]},
								"south": {"uv": [47, 32], "uv_size": [1, -2]},
								"west": {"uv": [47, 32], "uv_size": [1, -2]},
								"up": {"uv": [48, 30], "uv_size": [-1, 2]},
								"down": {"uv": [47, 32], "uv_size": [1, -2]}
							}
						},
						{
							"origin": [24.82573, 29.64442, 3.1],
							"size": [2.1, 5.4, 1.3],
							"pivot": [-13.22427, 42.14442, 10.05],
							"rotation": [0, 0, 22.5],
							"uv": {
								"north": {"uv": [47, 32], "uv_size": [1, -2]},
								"east": {"uv": [47, 32], "uv_size": [1, -2]},
								"south": {"uv": [47, 32], "uv_size": [1, -2]},
								"west": {"uv": [47, 32], "uv_size": [1, -2]},
								"up": {"uv": [48, 30], "uv_size": [-1, 2]},
								"down": {"uv": [47, 32], "uv_size": [1, -2]}
							}
						},
						{
							"origin": [24.82573, 29.64442, 4.6],
							"size": [2.1, 5.4, 1.3],
							"pivot": [-13.22427, 42.14442, 10.05],
							"rotation": [0, 0, 22.5],
							"uv": {
								"north": {"uv": [47, 32], "uv_size": [1, -2]},
								"east": {"uv": [47, 32], "uv_size": [1, -2]},
								"south": {"uv": [47, 32], "uv_size": [1, -2]},
								"west": {"uv": [47, 32], "uv_size": [1, -2]},
								"up": {"uv": [48, 30], "uv_size": [-1, 2]},
								"down": {"uv": [47, 32], "uv_size": [1, -2]}
							}
						},
						{
							"origin": [10.75884, 28.44194, -1.4],
							"size": [9.1, 15.6, 8.6],
							"pivot": [-14.29116, 41.84194, 9.25],
							"rotation": [0, 0, -22.5],
							"uv": {
								"north": {"uv": [44, 20], "uv_size": [4, 7]},
								"east": {"uv": [40, 20], "uv_size": [4, 7]},
								"south": {"uv": [52, 20], "uv_size": [4, 7]},
								"west": {"uv": [48, 20], "uv_size": [4, 7]},
								"up": {"uv": [48, 20], "uv_size": [-4, -4]},
								"down": {"uv": [44, 24], "uv_size": [4, 4]}
							}
						}
					]
				},
				{
					"name": "leftItem",
					"parent": "leftArm",
					"pivot": [16.31546, 24.1805, 2.5187]
				},
				{
					"name": "rightLeg",
					"parent": "root",
					"pivot": [-3.75833, 27.06768, 3.49657],
					"cubes": [
						{
							"origin": [-7.25, 13.62431, -2.07038],
							"size": [7, 12, 7],
							"pivot": [0, 19.12431, 6.17962],
							"rotation": [-22.5, 0, 0],
							"uv": {
								"north": {"uv": [4, 20], "uv_size": [4, 5]},
								"east": {"uv": [16, 52], "uv_size": [4, 5]},
								"south": {"uv": [4, 20], "uv_size": [4, 5]},
								"west": {"uv": [24, 52], "uv_size": [4, 5]},
								"up": {"uv": [24, 52], "uv_size": [-4, -4]},
								"down": {"uv": [20, 48], "uv_size": [4, 4]}
							}
						},
						{
							"origin": [-6.25, 13.87431, -3.57038],
							"size": [5, 6.5, 5],
							"pivot": [0, 19.12431, 6.17962],
							"rotation": [22.5, 0, 0],
							"uv": {
								"north": {"uv": [20, 55], "uv_size": [4, 5]},
								"east": {"uv": [20, 55], "uv_size": [4, 5]},
								"south": {"uv": [20, 55], "uv_size": [4, 5]},
								"west": {"uv": [20, 55], "uv_size": [4, 5]},
								"up": {"uv": [24, 60], "uv_size": [-4, -5]},
								"down": {"uv": [20, 55], "uv_size": [4, 5]}
							}
						},
						{
							"origin": [-6.8, 11, -0.75],
							"size": [6, 14, 6],
							"uv": {
								"north": {"uv": [20, 53], "uv_size": [4, 8]},
								"east": {"uv": [16, 53], "uv_size": [4, 8]},
								"south": {"uv": [28, 53], "uv_size": [4, 8]},
								"west": {"uv": [24, 53], "uv_size": [4, 8]},
								"down": {"uv": [20, 48], "uv_size": [4, 4]}
							}
						},
						{
							"origin": [-5.75, 8.25, -0.5],
							"size": [4, 3.5, 4],
							"uv": {
								"north": {"uv": [12, 24], "uv_size": [4, 4]},
								"east": {"uv": [12, 24], "uv_size": [4, 4]},
								"south": {"uv": [12, 24], "uv_size": [4, 4]},
								"west": {"uv": [12, 24], "uv_size": [4, 4]},
								"down": {"uv": [12, 24], "uv_size": [4, 4]}
							}
						},
						{
							"origin": [-5.25, 4.25, 0],
							"size": [3, 4, 3],
							"uv": {
								"north": {"uv": [4, 26], "uv_size": [4, 4]},
								"east": {"uv": [4, 26], "uv_size": [4, 4]},
								"south": {"uv": [4, 26], "uv_size": [4, 4]},
								"west": {"uv": [4, 26], "uv_size": [4, 4]},
								"down": {"uv": [4, 26], "uv_size": [4, 4]}
							}
						},
						{
							"origin": [-4.75, 0.25, 0.5],
							"size": [2, 4, 2],
							"uv": {
								"north": {"uv": [4, 28], "uv_size": [4, 4]},
								"east": {"uv": [4, 28], "uv_size": [4, 4]},
								"south": {"uv": [4, 28], "uv_size": [4, 4]},
								"west": {"uv": [4, 28], "uv_size": [4, 4]},
								"down": {"uv": [8, 16], "uv_size": [4, 4]}
							}
						}
					]
				},
				{
					"name": "leftLeg",
					"parent": "root",
					"pivot": [5.04167, 27.0677, 3.4966],
					"cubes": [
						{
							"origin": [1.75, 14.62431, -0.07038],
							"size": [7, 12, 7],
							"pivot": [0, 24.12431, 5.17962],
							"rotation": [-22.5, 0, 0],
							"uv": {
								"north": {"uv": [4, 20], "uv_size": [4, 5]},
								"east": {"uv": [0, 20], "uv_size": [4, 5]},
								"south": {"uv": [12, 20], "uv_size": [4, 5]},
								"west": {"uv": [8, 20], "uv_size": [4, 5]},
								"up": {"uv": [8, 20], "uv_size": [-4, -4]},
								"down": {"uv": [4, 16], "uv_size": [4, 4]}
							}
						},
						{
							"origin": [2.5, 13.87431, -5.57038],
							"size": [5, 6.5, 5],
							"pivot": [0, 24.12431, 5.17962],
							"rotation": [22.5, 0, 0],
							"uv": {
								"north": {"uv": [4, 23], "uv_size": [4, 5]},
								"east": {"uv": [4, 23], "uv_size": [4, 5]},
								"south": {"uv": [4, 23], "uv_size": [4, 5]},
								"west": {"uv": [4, 23], "uv_size": [4, 5]},
								"up": {"uv": [8, 28], "uv_size": [-4, -5]},
								"down": {"uv": [4, 23], "uv_size": [4, 5]}
							}
						},
						{
							"origin": [2, 11, -0.75],
							"size": [6, 14, 6],
							"uv": {
								"north": {"uv": [4, 21], "uv_size": [4, 8]},
								"east": {"uv": [0, 21], "uv_size": [4, 8]},
								"south": {"uv": [12, 21], "uv_size": [4, 8]},
								"west": {"uv": [8, 21], "uv_size": [4, 8]},
								"down": {"uv": [4, 16], "uv_size": [4, 4]}
							}
						},
						{
							"origin": [3, 8.25, -0.5],
							"size": [4, 3.5, 4],
							"uv": {
								"north": {"uv": [12, 24], "uv_size": [4, 4]},
								"east": {"uv": [12, 24], "uv_size": [4, 4]},
								"south": {"uv": [12, 24], "uv_size": [4, 4]},
								"west": {"uv": [12, 24], "uv_size": [4, 4]},
								"down": {"uv": [12, 24], "uv_size": [4, 4]}
							}
						},
						{
							"origin": [3.5, 4.25, 0],
							"size": [3, 4, 3],
							"uv": {
								"north": {"uv": [4, 26], "uv_size": [4, 4]},
								"east": {"uv": [4, 26], "uv_size": [4, 4]},
								"south": {"uv": [4, 26], "uv_size": [4, 4]},
								"west": {"uv": [4, 26], "uv_size": [4, 4]},
								"down": {"uv": [4, 26], "uv_size": [4, 4]}
							}
						},
						{
							"origin": [4, 0.25, 0.5],
							"size": [2, 4, 2],
							"uv": {
								"north": {"uv": [4, 28], "uv_size": [4, 4]},
								"east": {"uv": [4, 28], "uv_size": [4, 4]},
								"south": {"uv": [4, 28], "uv_size": [4, 4]},
								"west": {"uv": [4, 28], "uv_size": [4, 4]},
								"down": {"uv": [8, 16], "uv_size": [4, 4]}
							}
						}
					]
				}
			]
		}
	]
}